pyQuASAR/QuASAR_genotype.R
pyQuASAR/__init__.py
pyQuASAR/download.py
pyQuASAR/env.py
pyQuASAR/pyQuASAR.py
pyQuASAR-1.0.2.dist-info/LICENSE
pyQuASAR-1.0.2.dist-info/METADATA
pyQuASAR-1.0.2.dist-info/WHEEL
pyQuASAR-1.0.2.dist-info/entry_points.txt
pyQuASAR-1.0.2.dist-info/top_level.txt
pyQuASAR-1.0.2.dist-info/RECORD
