Metadata-Version: 2.1
Name: pyQuASAR
Version: 1.0.2
Summary: Wrap quasar for pipelines
Home-page: https://gitlab.com/aaylward/pyQuASAR
Author: Anthony Aylward
Author-email: aaylward@salk.edu
License: UNKNOWN
Platform: UNKNOWN
Classifier: Programming Language :: Python :: 3
Classifier: License :: OSI Approved :: MIT License
Classifier: Operating System :: OS Independent
License-File: LICENSE
Requires-Dist: biopython
Requires-Dist: gitpython
Requires-Dist: funcgenom
